wttrman/__init__.py
wttrman/app.py
wttrman/wttr.py
wttrman/yaml_file_handler.py
wttrman/resources/PYPI_README.md
wttrman/resources/configs/config.yaml
wttrman/resources/configs/locations.yaml
wttrman/resources/configs/themes.yaml
wttrman/resources/gifs/app_showcase.gif
wttrman/resources/images/wttrman-128.png
wttrman/resources/images/wttrman-16.png
wttrman/resources/images/wttrman-256.png
wttrman/resources/images/wttrman-32.png
wttrman/resources/images/wttrman-512.png
wttrman/resources/images/wttrman-64.png
wttrman-1.2.2.dist-info/METADATA
wttrman-1.2.2.dist-info/WHEEL
wttrman-1.2.2.dist-info/entry_points.txt
wttrman-1.2.2.dist-info/licenses/LICENSE
wttrman-1.2.2.dist-info/RECORD
