Metadata-Version: 2.4
Name: wttrman
Version: 1.2.2
Summary: GUI front-end to https://wttr.in/.
Author-email: Melvin Quick <melvinquick@proton.me>
License-Expression: MIT
License-File: LICENSE
Requires-Python: >=3.12
Requires-Dist: pyside6>=6.8.2.1
Requires-Dist: pyyaml>=6.0.2
Requires-Dist: requests>=2.32.3
